[
  {
    "place_id": "subdivision:libya:sabha",
    "image_url": "https://images.unsplash.com/photo-1639862288281-e3bb885b6022?crop=entropy&cs=tinysrgb&fit=max&fm=jpg&ixid=M3w5MTYzNzR8MHwxfHNlYXJjaHwxfHxTYWJoYSUyMExpYnlhfGVufDF8MHx8fDE3ODQ3MTkzMDN8MA&ixlib=rb-4.1.0&q=80&w=1080",
    "photographer_name": "Moayad Zaghdani",
    "photographer_url": "https://unsplash.com/@moayadzaghdani?utm_source=freebase&utm_medium=referral",
    "source_url": "https://unsplash.com/photos/an-aerial-view-of-a-city-street-at-night-gQyl-FuFxBs?utm_source=freebase&utm_medium=referral",
    "cached_at": "2026-07-22T11:21:43Z"
  }
]
