[
  {
    "place_id": "city:algeria:bejaia:bejaia",
    "image_url": "https://images.unsplash.com/photo-1535585538107-e457d37fbde5?crop=entropy&cs=tinysrgb&fit=max&fm=jpg&ixid=M3w5MTYzNzR8MHwxfHNlYXJjaHwxfHxCZWphaWElMjBBbGdlcmlhfGVufDF8MHx8fDE3ODA2OTA1NTd8MA&ixlib=rb-4.1.0&q=80&w=1080",
    "photographer_name": "Walid Amghar",
    "photographer_url": "https://unsplash.com/@wixou?utm_source=freebase&utm_medium=referral",
    "source_url": "https://unsplash.com/photos/aerial-photography-of-city-8Bw3FnqPmp8?utm_source=freebase&utm_medium=referral",
    "cached_at": "2026-06-05T20:15:58Z"
  }
]
