[
  {
    "place_id": "city:ecuador:imbabura:ibarra",
    "image_url": "https://images.unsplash.com/photo-1745607979780-bc83148ba07b?crop=entropy&cs=tinysrgb&fit=max&fm=jpg&ixid=M3w5MTYzNzR8MHwxfHNlYXJjaHwyfHxJYmFycmElMjBJbWJhYnVyYXxlbnwxfDB8fHwxNzc5ODc4MDkzfDA&ixlib=rb-4.1.0&q=80&w=1080",
    "photographer_name": "Asso Myron",
    "photographer_url": "https://unsplash.com/@assomyron?utm_source=freebase&utm_medium=referral",
    "source_url": "https://unsplash.com/photos/a-man-holds-a-carved-object-on-stage-VDQ5q7D7mVI?utm_source=freebase&utm_medium=referral",
    "cached_at": "2026-05-27T10:34:53Z"
  }
]
