[
  {
    "place_id": "city:benin:mono:lokossa",
    "image_url": "https://images.unsplash.com/photo-1753818269652-2f2c5d11d3d1?crop=entropy&cs=tinysrgb&fit=max&fm=jpg&ixid=M3w5MTYzNzR8MHwxfHNlYXJjaHwxfHxMb2tvc3NhJTIwQmVuaW58ZW58MXwwfHx8MTc4MDAzMDA0MHww&ixlib=rb-4.1.0&q=80&w=1080",
    "photographer_name": "Greg Keelen",
    "photographer_url": "https://unsplash.com/@greg_keelen?utm_source=freebase&utm_medium=referral",
    "source_url": "https://unsplash.com/photos/a-statue-stands-near-buildings-on-the-water-bFSTPlZnMyA?utm_source=freebase&utm_medium=referral",
    "cached_at": "2026-05-29T04:47:20Z"
  }
]
