[
  {
    "place_id": "city:indonesia:east_nusa_tenggara:maumere",
    "image_url": "https://images.unsplash.com/photo-1608703606211-09bf29d5f256?crop=entropy&cs=tinysrgb&fit=max&fm=jpg&ixid=M3w5MTYzNzR8MHwxfHNlYXJjaHwxfHxNYXVtZXJlJTIwSW5kb25lc2lhfGVufDF8MHx8fDE3ODQ0MTI1NTJ8MA&ixlib=rb-4.1.0&q=80&w=1080",
    "photographer_name": "Nicolas Stevan",
    "photographer_url": "https://unsplash.com/@nicolastan_563?utm_source=freebase&utm_medium=referral",
    "source_url": "https://unsplash.com/photos/brown-mountain-under-blue-sky-during-daytime-H3gMJUy7a-I?utm_source=freebase&utm_medium=referral",
    "cached_at": "2026-07-18T22:09:12Z"
  }
]
