[
  {
    "place_id": "subdivision:malaysia:malacca",
    "image_url": "https://images.unsplash.com/photo-1605986152687-c31d1372d560?crop=entropy&cs=tinysrgb&fit=max&fm=jpg&ixid=M3w5MTYzNzR8MHwxfHNlYXJjaHwxfHxNYWxhY2NhJTIwTWFsYXlzaWF8ZW58MXwwfHx8MTc3NzAzOTg0OXww&ixlib=rb-4.1.0&q=80&w=1080",
    "photographer_name": "Ahmed Gowda",
    "photographer_url": "https://unsplash.com/@ahmedgowda?utm_source=freebase&utm_medium=referral",
    "source_url": "https://unsplash.com/photos/aerial-view-of-city-buildings-during-daytime-M0SMwqX9YCE?utm_source=freebase&utm_medium=referral",
    "cached_at": "2026-04-24T14:10:49Z"
  }
]
