[
  {
    "place_id": "subdivision:albania:diber",
    "image_url": "https://images.unsplash.com/photo-1687294089160-97d373b3db2c?crop=entropy&cs=tinysrgb&fit=max&fm=jpg&ixid=M3w5MTYzNzR8MHwxfHNlYXJjaHwxfHxEaWJlciUyMEFsYmFuaWF8ZW58MXwwfHx8MTc3NzYwOTkyMnww&ixlib=rb-4.1.0&q=80&w=1080",
    "photographer_name": "Vladan Raznatovic",
    "photographer_url": "https://unsplash.com/@vladanraznatovic?utm_source=freebase&utm_medium=referral",
    "source_url": "https://unsplash.com/photos/a-bunch-of-buildings-that-are-on-the-side-of-a-hill-2qVfOdZ6YAU?utm_source=freebase&utm_medium=referral",
    "cached_at": "2026-05-01T04:32:02Z"
  }
]
