[
  {
    "place_id": "city:kyrgyzstan:issyk_kul:cholpon_ata",
    "image_url": "https://images.unsplash.com/photo-1561287437-c69a30664793?crop=entropy&cs=tinysrgb&fit=max&fm=jpg&ixid=M3w5MTYzNzR8MHwxfHNlYXJjaHwyfHxDaG9scG9uJTIwQXRhJTIwSXNzeWslMjBLdWx8ZW58MXwwfHx8MTc4NDYzMjgxMHww&ixlib=rb-4.1.0&q=80&w=1080",
    "photographer_name": "prayer flags",
    "photographer_url": "https://unsplash.com/@rishishankar?utm_source=freebase&utm_medium=referral",
    "source_url": "https://unsplash.com/photos/houses-on-mountain-0ICxgY6vdCA?utm_source=freebase&utm_medium=referral",
    "cached_at": "2026-07-21T11:20:10Z"
  }
]
