[
  {
    "place_id": "city:bangladesh:khulna:mongla",
    "image_url": "https://images.unsplash.com/photo-1674236537020-9ccf3b9841a9?crop=entropy&cs=tinysrgb&fit=max&fm=jpg&ixid=M3w5MTYzNzR8MHwxfHNlYXJjaHwxfHxNb25nbGElMjBLaHVsbmF8ZW58MXwwfHx8MTc4MDkxNzc5OHww&ixlib=rb-4.1.0&q=80&w=1080",
    "photographer_name": "Md Arafat Ul Alam",
    "photographer_url": "https://unsplash.com/@arafatux?utm_source=freebase&utm_medium=referral",
    "source_url": "https://unsplash.com/photos/a-body-of-water-with-a-boat-in-the-distance-lUBwA5O-qVM?utm_source=freebase&utm_medium=referral",
    "cached_at": "2026-06-08T11:23:18Z"
  }
]
