[
  {
    "place_id": "subdivision:indonesia:west_java",
    "image_url": "https://images.unsplash.com/photo-1556691951-e9ca75040056?crop=entropy&cs=tinysrgb&fit=max&fm=jpg&ixid=M3w5MTYzNzR8MHwxfHNlYXJjaHwxfHxXZXN0JTIwSmF2YSUyQyUyMEluZG9uZXNpYSUyMHRyYXZlbHxlbnwxfDB8fHwxNzc1NTg5NzMzfDA&ixlib=rb-4.1.0&q=80&w=1080",
    "photographer_name": "Bayu Syaits",
    "photographer_url": "https://unsplash.com/@bayusyaits?utm_source=freebase&utm_medium=referral",
    "source_url": "https://unsplash.com/photos/trees-near-river-zrg0W-oFuHQ?utm_source=freebase&utm_medium=referral",
    "cached_at": ""
  }
]
